Workbook

Sheet Dashboard
B2: HEXALEVEL — MONTHLY REVENUE DASHBOARD
B3: All values update automatically — add rows to Projects / Revenue Split / Expenses
B5: TOTAL REVENUE (PKR) | F5: COMPANY SHARE (50%) | J5: TEAM SHARE (50%) | M5: TOTAL PURCHASES
B6: ='Revenue Split'!B24 | F6: ='Revenue Split'!C24 | J6: ='Revenue Split'!D24 | M6: =Expenses!C10
B8: NET PROFIT | F8: TOTAL PROJECTS | J8: PAYMENTS RECEIVED | M8: SEND MONEY TOTAL
B9: =F6-M6-M9 | F9: =COUNTA(Projects!A3:A24) | J9: =COUNTIF(Projects!G3:G24, "Received") | M9: ='Send Money'!B12
B11: NEW SPLIT — FROM 1 SEP 2026 (Company 30% · Shaista / Amara / Urooj 23.33% each)
B13: TOTAL REVENUE (PKR) | F13: COMPANY SHARE (Total) | J13: TEAM SHARE (Total) | M13: TOTAL PURCHASES
B14: ='Revenue Split'!B30 | F14: ='Revenue Split'!C30 | J14: =SUM('Revenue Split'!D30:F30) | M14: =Expenses!C15
B16: NET PROFIT | F16: TOTAL PROJECTS | J16: PAYMENTS RECEIVED | M16: SEND MONEY TOTAL
B17: =F14-M14-M17 | F17: =COUNTA('Revenue Split'!A29:A29) | J17: =COUNTIF('Revenue Split'!G29:G29, "Received") | M17: ='Send Money'!B16
B19: OVERALL SUMMARY (Old + New Combined)
B21: OVERALL REVENUE (PKR) | F21: OVERALL NET PROFIT | I21: TOTAL PROJECTS | L21: PAYMENTS RECEIVED
B22: =B6+B14 | F22: =B9+B17 | I22: =F9+F17 | L22: =J9+J17

Sheet Projects
A1: HEXALEVEL — CLIENT PROJECTS TRACKER
A2: Project Start | B2: Client Name | C2: Project Name | D2: Service Type | E2: Amount | F2: Currency | G2: Payment Status | H2: Payment Date | I2: Notes | J2: Bank
A3: Dec 2025 | B3: Ranked Skill | C3: Mortgage Leads flow | D3: CRM | E3: 25000 | F3: PKR | G3: Received | H3: 12-Jan-2026 | I3: Received | J3: Meezan
A4: Jan 2026 | B4: India | C4: Crm +Wp | D4: Both | E4: 15000 | F4: INR | G4: Received | H4: 20-Feb-2026 | I4: Received | J4: Payoneer
A5: Jan 2026 | B5: USA | C5: GHL all services | D5: CRM | E5: 350 | F5: USD | G5: Pending | I5: Waiting for payment
A6: Jan 2026 | B6: Lahore | C6: Life insurance | D6: CRM | E6: 40000 | F6: PKR | G6: Received | H6: 21-Feb-2026 | I6: Received | J6: HBL
A7: Jan 2026 | B7: Mehroz | C7: GHL Work | D7: CRM | E7: 28600 | F7: PKR | G7: Received | H7: 3 Mar 2026 | I7: Received | J7: Meezan
A8: Dec 2025 | B8: Waleed | C8: Seo site | D8: WP | E8: 29000 | F8: PKR | G8: Received | H8: 25 Feb 2026 | I8: Received | J8: Nayapay
A9: Mar 2026 | B9: Upwork | C9: Funnel designing | D9: CRM | E9: 9382 | F9: PKR | G9: Received | H9: 15 Mar 2026 | I9: Received | J9: Meezan
A10: Mar 2026 | B10: India | C10: Crm +Wp | D10: Both | E10: 15000 | F10: INR | G10: Received | H10: 20-Feb-2026 | I10: Received | J10: Payoneer
A11: Mar 2026 | B11: Mehroz | C11: A2p | D11: CRM | E11: 19250 | F11: PKR | G11: Received | H11: 27 Mar 2026 | I11: Received | J11: Meezan
A12: April 2026 | B12: haris | C12: GHL | D12: CRM | E12: 46334 | F12: PKR | G12: Received | H12: 6 April 2026 | I12: Received | J12: Payoneer
A13: April 2026 | B13: Mehroz | C13: A2p | D13: CRM | E13: 33600 | F13: PKR | G13: Received | H13: 16 April 2026 | I13: Received | J13: Meezan
A14: April 2026 | B14: India | C14: CRM+WP | D14: Both | E14: 42199 | F14: PKR | G14: Received | H14: 24 April 2026 | I14: Received | J14: Payoneer
A15: April 2026 | B15: Usa + Fiver | C15: GHL | D15: CRM | E15: 80163 | F15: PKR | G15: Received | H15: 25 April 2026 | I15: Received | J15: HBL
A16: May 2026 | B16: Haris | C16: GHL | D16: CRM | E16: 44401 | F16: PKR | G16: Received | H16: 3 May 2026 | I16: Received | J16: Payoneer
A17: May 2026 | B17: Usa | C17: GHL | D17: CRM | E17: 85616 | F17: PKR | G17: Received | H17: 15 May 2026 | I17: Received | J17: Askari
... A24: 27/10/2026 | B24: USA | C24: GHL | D24: CRM | E24: 36099 | F24: PKR | G24: Received | H24: 27/10/2026 | I24: Received | J24: Askari
A25: TOTAL | E25: =SUM(E3:E24)
A26: 19/10/26 | B26: Umair | C26: GHL | D26: CRM | E26: 20000 | F26: PKR | G26: Received | H26: 19/10/26 | I26: Received | J26: Meezan

Sheet Revenue Split
A1: HEXALEVEL — REVENUE SPLIT | 50% Company · 50% Team
A2: Month | B2: Amount (PKR) | C2: Company 50% | D2: Team 50% | E2: Status | F2: Date Received | G2: Shaista | H2: Amara | I2: Tax on Transfer
A3: DEC | B3: 25000 | C3: =B3*0.5 | D3: =B3*0.5 | E3: Received | F3: 26 Jan 2026 | G3: Nayapay | H3: Askari
A4: FEB | B4: 54541 | C4: =B4*0.5 | D4: =B4*0.5 | E4: Received | F4: 20 Feb 2026 | G4: Nayapay | H4: Askari
A5: FEB | B5: 40000 | C5: =B5*0.5 | D5: =B5*0.5 | E5: Received | F5: 21 Feb 2026 | G5: HBI | H5: Askari
A6: FEB | B6: 29000 | C6: =B6*0.5 | D6: =B6*0.5 | E6: Received | F6: 25 Feb 2026 | G6: Nayapay | H6: Askari
A7: March | B7: 28600 | C7: =B7*0.5 | D7: =B7*0.5 | E7: Received | F7: 3 Mar 2026 | G7: Nayapay | H7: Nayapay
A8: March | B8: 9382 | C8: =B8*0.5 | D8: =B8*0.5 | E8: Received | F8: 15 Mar 2026 | G8: Nayapay | H8: Nayapay
A9: March | B9: 42671 | C9: =B9*0.5 | D9: =B9*0.5 | E9: Received | F9: 25 Mar 2026 | G9: Nayapay | H9: Nayapay
A10: March | B10: 19250 | C10: =B10*0.5 | D10: =B10*0.5 | E10: Received | F10: 27 Mar 2026 | G10: Nayapay | H10: Nayapay
A11: April | B11: 46334 | C11: =B11*0.5 | D11: =B11*0.5 | E11: Received | F11: 6 Apr 2026 | G11: Nayapay | H11: Askari
A12: April | B12: 33600 | C12: =B12*0.5 | D12: =B12*0.5 | E12: Received | F12: 16 Apr 2026 | G12: Nayapay | H12: Askari
A13: April | B13: 42199 | C13: =B13*0.5 | D13: =B13*0.5 | E13: Received | F13: 24 Apr 2026 | G13: Nayapay | H13: Askari
A14: April | B14: 80163 | C14: =B14*0.5 | D14: =B14*0.5 | E14: Received | F14: 25 Apr 2026 | G14: Hbl | H14: Askari
... A23: Sep | B23: 36099 | C23: =B23*0.5 | D23: =B23*0.5 | E23: Received | F23: 27 Oct 2026 | G23: Cutting | H23: Askari
A24: TOTAL | B24: =SUM(B3:B23) | C24: =SUM(C3:C23) | D24: =SUM(D3:D23)
A27: HEXALEVEL — REVENUE SPLIT (NEW MODEL, effective 1 Sep 2026) | Company 30% · Shaista 23.33% · Amara 23.33% · Urooj 23.33%
A28: Month | B28: Amount (PKR) | C28: Company 30% | D28: Shaista 23.33% | E28: Amara 23.33% | F28: Urooj 23.33% | G28: Status | H28: Date Received | I28: Shaista | J28: Amara | K28: Urooj | L28: Tax on Transfer | M28: Notes
A29: Oct | B29: 20000 | C29: =B29*0.30 | D29: =B29*(7/30) | E29: =B29*(7/30) | F29: =B29*(7/30) | G29: Received | H29: 19/10/26 | I29: Cutting | J29: Nayapay | K29: UBL
A30: TOTAL | B30: =SUM(B29:B29) | C30: =SUM(C29:C29) | D30: =SUM(D29:D29) | E30: =SUM(E29:E29) | F30: =SUM(F29:F29)

Sheet Expenses
A1: PURCHASES — Items & Prices
A2: Item / Purchase | B2: Name / Link | C2: Price (PKR)
A3: Domain | B3: theghlvideo.com | C3: 3314.4
A4: Upwork Connects | B4: $15 | C4: 4830
A5: Fiver Course | B5: Chain solution | C5: 1999
A6: 6 course Leads generation | B6: 6/6 course | C6: 1200
A7: Buy Crm | B7: Guarantee Crm | C7: 370
A8: BUY EMAIL THEGHLVIDEO | C8: 2533.82
A9: Renew hexalevel Domain | C9: 4955
A10: TOTAL | C10: =SUM(C3:C9)
A12: NEW PURCHASES — Items & Prices (from 1 Sep 2026, split 3 ways)
A13: Item / Purchase | B13: Name / Link | C13: Price (PKR)
A15: TOTAL | C15: =SUM(C14:C14)

Sheet Send Money
A1: SEND MONEY — Payments Made
A2: Send Money To | B2: Amount Sent (PKR)
A3: Send Sundas for email testing | B3: 1200
A4: Meeting Fiver with Ahsan | B4: 10000
A5: Waqar Udhar | B5: 3250
A12: TOTAL | B12: =SUM(B3:B11)
A14: NEW SEND MONEY — Payments Made (from 1 Sep 2026, split 3 ways)
A15: Send Money To | B15: Amount Sent (PKR)
A16: TOTAL | B16: =SUM(B15:B15)

Sheet Scenario C & Net Profit
A1: HEXALEVEL — SCENARIO C (3 REGISTERED MEMBERS · 2 WORKING · 1 SKIPPED)
A2: Rule: Skipped member gets 0 direct share. Unallocated share (23.33%) goes to Company (53.33%). In Net Profit, surplus is credited ONLY to working members.
A3: Project ID | B3: Client Name | C3: Amount (PKR) | D3: Status | E3: Shaista (23.33%) | F3: Amara (23.33%) | G3: Urooj (23.33%) | H3: Skipped Share to Co (23.33%) | I3: Total Co Share (53.33%) | J3: Notes
A4: PRJ-023 | B4: Umair (All 3 Active) | C4: 20000 | D4: Received | E4: 4666.67 | F4: 4666.67 | G4: 4666.67 | H4: 0 | I4: 6000 | J4: Scenario B (All 3 Active)
A5: PRJ-024 | B5: Demo Client A | C5: 50000 | D5: Received | E5: 11666.67 | F5: 11666.67 | G5: 0 | H5: 11666.67 | I5: 26666.67 | J5: Urooj Skipped -> Surplus to Co
A6: PRJ-025 | B6: Demo Client B | C6: 30000 | D6: Received | E6: 7000 | F6: 0 | G6: 7000 | H6: 7000 | I6: 16000 | J6: Amara Skipped -> Surplus to Co
A7: TOTAL | C7: =SUM(C4:C6) | E7: =SUM(E4:E6) | F7: =SUM(F4:F6) | G7: =SUM(G4:G6) | H7: =SUM(H4:H6) | I7: =SUM(I4:I6)
A10: PARTNER NET PROFIT STATEMENTS (Including Scenario C Attribution)
A11: Partner Name | B11: Direct Project Payouts | C11: Scenario C Surplus Credit | D11: Company Net Distribution | E11: Total Deductions | F11: Final Net Profit | G11: Status
A12: Shaista (Co-Founder) | B12: =SUM('Revenue Split'!D3:D23)*0.5 + E7 | C12: =H4*0.5 + H5*1.0 | D12: =('Revenue Split'!C24 + 'Revenue Split'!C30 - Expenses!C10 - Expenses!C15 - 'Send Money'!B12)/3 | E12: 0 | F12: =B12+C12+D12-E12 | G12: Active
A13: Amara (Co-Founder) | B13: =SUM('Revenue Split'!D3:D23)*0.5 + F7 | C13: =H4*0.5 + H6*1.0 | D13: =('Revenue Split'!C24 + 'Revenue Split'!C30 - Expenses!C10 - Expenses!C15 - 'Send Money'!B12)/3 | E13: 0 | F13: =B13+C13+D13-E13 | G13: Active
A14: Urooj (Partner) | B14: =G7 | C14: =H6*1.0 | D14: =('Revenue Split'!C24 + 'Revenue Split'!C30 - Expenses!C10 - Expenses!C15 - 'Send Money'!B12)/3 | E14: 0 | F14: =B14+C14+D14-E14 | G14: Active
